cli_satellite
