Metadata-Version: 1.0
Name: HiveMind-cli
Version: 0.4.1
Summary: Mycroft Remote Cli
Home-page: https://github.com/OpenJarbas/HiveMind-cli
Author: jarbasAI
Author-email: jarbasai@mailfence.com
License: MIT
Platform: UNKNOWN
